ColorizedPrint.py
ColorizedPrint-0.0.2.dist-info/METADATA
ColorizedPrint-0.0.2.dist-info/WHEEL
ColorizedPrint-0.0.2.dist-info/top_level.txt
ColorizedPrint-0.0.2.dist-info/RECORD
