Metadata-Version: 2.1
Name: ColorizedPrint
Version: 0.0.2
Summary: This is a modified version of a print function of a python
Home-page: UNKNOWN
Author: Abhay Vachhani
Author-email: UNKNOWN
License: UNKNOWN
Keywords: Abhay,Abhay Vachhani,Abhay28,Colorized Print,ColorizedPrint,print
Platform: UNKNOWN
Requires-Dist: colorama
